ishareslib/__init__.py
ishareslib/client.py
ishareslib/core/__init__.py
ishareslib/core/proxy_adapter.py
ishareslib/core/user_agent_adapter.py
ishareslib/ext/__init__.py
ishareslib/ext/proxy/__init__.py
ishareslib/ext/proxy/webshare_proxy_adapter.py
ishareslib/ext/user_agent/__init__.py
ishareslib/ext/user_agent/human_user_agent_adapter.py
ishareslib-0.1.0.dist-info/LICENSE
ishareslib-0.1.0.dist-info/METADATA
ishareslib-0.1.0.dist-info/WHEEL
ishareslib-0.1.0.dist-info/top_level.txt
ishareslib-0.1.0.dist-info/RECORD
