Metadata-Version: 2.1
Name: ishareslib
Version: 0.1.0
Summary: A library for reading data from the ishares product family.
Home-page: https://github.com/iamfj/ishareslib/
Author: Fabian Jocks (iamfj) <dev@jocks.io>
License: UNKNOWN
Platform: UNKNOWN
License-File: LICENSE
Requires-Dist: requests (==2.27.1)
Requires-Dist: types-requests (==2.27.14)
Requires-Dist: pandas (==1.4.1)
Requires-Dist: pandas-stubs (==1.2.0.53)
Provides-Extra: dev
Requires-Dist: pre-commit (==2.17.0) ; extra == 'dev'
Requires-Dist: black (==22.1.0) ; extra == 'dev'
Requires-Dist: isort (==5.10.1) ; extra == 'dev'
Requires-Dist: flake8 (==4.0.1) ; extra == 'dev'
Requires-Dist: mypy (==0.941) ; extra == 'dev'
Provides-Extra: test
Requires-Dist: pre-commit (==2.17.0) ; extra == 'test'
Requires-Dist: black (==22.1.0) ; extra == 'test'
Requires-Dist: isort (==5.10.1) ; extra == 'test'
Requires-Dist: flake8 (==4.0.1) ; extra == 'test'
Requires-Dist: mypy (==0.941) ; extra == 'test'
Requires-Dist: Faker (==13.3.2) ; extra == 'test'
Requires-Dist: pytest (==7.1.0) ; extra == 'test'
Requires-Dist: pytest-cov (==3.0.0) ; extra == 'test'
Requires-Dist: requests-mock (==1.9.3) ; extra == 'test'
Requires-Dist: coverage (==6.3.2) ; extra == 'test'
